amatino/__init__.py
amatino/account.py
amatino/am_type.py
amatino/amatino_alpha.py
amatino/amatino_error.py
amatino/api_error.py
amatino/balance.py
amatino/color.py
amatino/constraint_error.py
amatino/custom_unit.py
amatino/decodable.py
amatino/denominated.py
amatino/denomination.py
amatino/entity.py
amatino/entity_list.py
amatino/entry.py
amatino/global_unit.py
amatino/ledger.py
amatino/ledger_order.py
amatino/ledger_row.py
amatino/missing_key.py
amatino/performance.py
amatino/permissions_graph.py
amatino/position.py
amatino/recursive_balance.py
amatino/recursive_ledger.py
amatino/region.py
amatino/session.py
amatino/side.py
amatino/state.py
amatino/transaction.py
amatino/tree.py
amatino/tree_node.py
amatino/tx_version_list.py
amatino/unexpected_response_type.py
amatino/user.py
amatino/user_list.py
amatino/_internal/__init__.py
amatino/_internal/_am_time.py
amatino/_internal/_api_encodable.py
amatino/_internal/_api_request.py
amatino/_internal/_data_package.py
amatino/_internal/_new_custom_unit_arguments.py
amatino/_internal/_new_entity_arguments.py
amatino/_internal/_new_session_arguments.py
amatino/_internal/_new_transaction_arguments.py
amatino/_internal/_request_headers.py
amatino/_internal/_session_credentials.py
amatino/_internal/_signature.py
amatino/_internal/_url_parameters.py
amatino/_internal/_url_target.py
amatino/internal/__init__.py
amatino/internal/am_amount.py
amatino/internal/am_time.py
amatino/internal/api_request.py
amatino/internal/balance_protocol.py
amatino/internal/constrained_integer.py
amatino/internal/constrained_string.py
amatino/internal/credentials.py
amatino/internal/data_package.py
amatino/internal/decodable.py
amatino/internal/disposition.py
amatino/internal/encodable.py
amatino/internal/entity_update_arguments.py
amatino/internal/http_method.py
amatino/internal/immutable.py
amatino/internal/ledger_iterator.py
amatino/internal/request_headers.py
amatino/internal/session_create_arguments.py
amatino/internal/session_decodable.py
amatino-0.0.19.dist-info/METADATA
amatino-0.0.19.dist-info/WHEEL
amatino-0.0.19.dist-info/top_level.txt
amatino-0.0.19.dist-info/RECORD
