Metadata-Version: 2.1
Name: amatino
Version: 0.0.19
Summary: Bindings for the Amatino API, an accounting & financial data engine
Home-page: https://amatino.io
Author: Amatino
Author-email: hugh@amatino.io
License: UNKNOWN
Project-URL: Twitter, https://twitter.com/amatinoapi
Project-URL: Github Repository, https://github.com/amatino-code/amatino-python
Project-URL: Subscribe, https://amatino.io/subscribe
Project-URL: Getting Started Guide, https://amatino.io/articles/getting-started
Project-URL: Discuss, https://amatino.io/discussion
Project-URL: Development Newsletter, https://amatino.io/newsletter
Keywords: amatino api bindings accounting double-entry accounts library
Platform: UNKNOWN
Classifier: Development Status :: 2 - Pre-Alpha
Classifier: Intended Audience :: Developers
Classifier: License :: OSI Approved :: MIT License
Classifier: Natural Language :: English
Classifier: Programming Language :: Python :: 3 :: Only
Classifier: Programming Language :: Python :: 3.6
Classifier: Programming Language :: Python :: 3.7
Classifier: Programming Language :: Python :: 3.8
Classifier: Programming Language :: Python :: 3.9
Classifier: Programming Language :: Python :: 3.10
Classifier: Operating System :: OS Independent
Classifier: Topic :: Office/Business :: Financial :: Accounting
Classifier: Topic :: Software Development :: Libraries
Requires-Python: >=3.6
Requires-Dist: typing
